dubborequests/__init__.py
dubborequests/api.py
dubborequests/config.py
dubborequests/util.py
dropbugmaker-0.1.dist-info/LICENSE
dropbugmaker-0.1.dist-info/METADATA
dropbugmaker-0.1.dist-info/WHEEL
dropbugmaker-0.1.dist-info/top_level.txt
dropbugmaker-0.1.dist-info/RECORD
