Metadata-Version: 2.1
Name: dropbugmaker
Version: 0.1
Summary: drop bugmaker platfrom
Home-page: https://github.com/airdrop11t/airdrop_test
Author: JackTest
Author-email: workspaceelojack@gmail.com
License: MIT
Classifier: Programming Language :: Python :: 3
Classifier: License :: OSI Approved :: MIT License
Classifier: Operating System :: OS Independent
Requires-Python: >=3.7.0
License-File: LICENSE
Requires-Dist: kazoo
Requires-Dist: pyyaml
Requires-Dist: requests
